{
  "kind": "collectionType",
  "collectionName": "questions",
  "info": {
    "name": "Question",
    "description": ""
  },
  "options": {
    "increments": true,
    "timestamps": true,
    "draftAndPublish": true
  },
  "pluginOptions": {},
  "attributes": {
    "Question_sentence": {
      "type": "text"
    },
    "choices": {
      "type": "component",
      "repeatable": true,
      "component": "question-choices.choices"
    },
    "Explanation": {
      "type": "text"
    },
    "language": {
      "model": "language"
    },
    "output": {
      "type": "text"
    }
  }
}
